roadtools/roadrecon/__init__.py
roadtools/roadrecon/gather.py
roadtools/roadrecon/main.py
roadtools/roadrecon/server.py
roadtools/roadrecon/dist_gui/3rdpartylicenses.txt
roadtools/roadrecon/dist_gui/index.html
roadtools/roadrecon/dist_gui/main.85359eb82b074d01.js
roadtools/roadrecon/dist_gui/polyfills.3434510fb5b4de7e.js
roadtools/roadrecon/dist_gui/runtime.a7446122f8b27a4d.js
roadtools/roadrecon/dist_gui/styles.9afce2c3ef55c87a.css
roadtools/roadrecon/dist_gui/assets/roadicon.png
roadtools/roadrecon/dist_gui/assets/rt_logoonly_margin.svg
roadtools/roadrecon/dist_gui/assets/rt_transparent.svg
roadtools/roadrecon/plugins/__init__.py
roadtools/roadrecon/plugins/bloodhound.py
roadtools/roadrecon/plugins/policies.py
roadtools/roadrecon/plugins/road2timeline.py
roadtools/roadrecon/plugins/road2timeline.yaml
roadtools/roadrecon/plugins/xlsexport.py
roadrecon-1.7.3.dist-info/METADATA
roadrecon-1.7.3.dist-info/WHEEL
roadrecon-1.7.3.dist-info/entry_points.txt
roadrecon-1.7.3.dist-info/top_level.txt
roadrecon-1.7.3.dist-info/RECORD
