Metadata-Version: 2.4
Name: roadrecon
Version: 1.7.3
Summary: Azure AD recon for red and blue
Home-page: https://github.com/dirkjanm/ROADtools/
Author: Dirk-jan Mollema
Author-email: dirkjan@dirkjanm.io
License: MIT
Classifier: Intended Audience :: Information Technology
Classifier: Programming Language :: Python :: 3
Classifier: Programming Language :: Python :: 3.9
Classifier: Programming Language :: Python :: 3.10
Classifier: Programming Language :: Python :: 3.11
Classifier: Programming Language :: Python :: 3.12
Classifier: Programming Language :: Python :: 3.13
Requires-Dist: roadlib>=0.21
Requires-Dist: flask<3
Requires-Dist: sqlalchemy>=1.4
Requires-Dist: marshmallow<4
Requires-Dist: flask-sqlalchemy>=2.5
Requires-Dist: flask-marshmallow
Requires-Dist: flask-cors
Requires-Dist: marshmallow-sqlalchemy>=0.29
Requires-Dist: aiohttp
Requires-Dist: openpyxl
Provides-Extra: road2timeline
Requires-Dist: pyyaml; extra == "road2timeline"
Requires-Dist: numpy; extra == "road2timeline"
Requires-Dist: pandas; extra == "road2timeline"
Dynamic: author
Dynamic: author-email
Dynamic: classifier
Dynamic: home-page
Dynamic: license
Dynamic: provides-extra
Dynamic: requires-dist
Dynamic: summary
